{
  "schema_version": "1.0",
  "engine": "qutip",
  "solver": "me",
  "dimension": 2,
  "t_end": 1000.0,
  "dt": 0.25,
  "payload": {
    "model_type": "qubit_network",
    "num_qubits": 1,
    "qubit_freqs_hz": [
      0.0
    ],
    "couplings": [],
    "controls": [
      {
        "channel": "XY0",
        "target": 0,
        "axis": "x",
        "times": [
          0.0,
          1.0,
          2.0,
          3.0,
          4.0,
          5.0,
          6.0,
          7.0,
          8.0,
          9.0,
          10.0,
          11.0,
          12.0,
          13.0,
          14.0,
          15.0,
          16.0,
          17.0,
          18.0,
          19.0,
          20.0,
          21.0,
          22.0,
          23.0,
          24.0,
          25.0,
          26.0,
          27.0,
          28.0,
          29.0,
          30.0,
          31.0,
          32.0,
          33.0,
          34.0,
          35.0,
          36.0,
          37.0,
          38.0,
          39.0,
          40.0,
          41.0,
          42.0,
          43.0,
          44.0,
          45.0,
          46.0,
          47.0,
          48.0,
          49.0,
          50.0,
          51.0,
          52.0,
          53.0,
          54.0,
          55.0,
          56.0,
          57.0,
          58.0,
          59.0,
          60.0,
          61.0,
          62.0,
          63.0,
          64.0,
          65.0,
          66.0,
          67.0,
          68.0,
          69.0,
          70.0,
          71.0,
          72.0,
          73.0,
          74.0,
          75.0,
          76.0,
          77.0,
          78.0,
          79.0,
          80.0,
          81.0,
          82.0,
          83.0,
          84.0,
          85.0,
          86.0,
          87.0,
          88.0,
          89.0,
          90.0,
          91.0,
          92.0,
          93.0,
          94.0,
          95.0,
          96.0,
          97.0,
          98.0,
          99.0,
          100.0,
          101.0,
          102.0,
          103.0,
          104.0,
          105.0,
          106.0,
          107.0,
          108.0,
          109.0,
          110.0,
          111.0,
          112.0,
          113.0,
          114.0,
          115.0,
          116.0,
          117.0,
          118.0,
          119.0,
          120.0,
          121.0,
          122.0,
          123.0,
          124.0,
          125.0,
          126.0,
          127.0,
          128.0,
          129.0,
          130.0,
          131.0,
          132.0,
          133.0,
          134.0,
          135.0,
          136.0,
          137.0,
          138.0,
          139.0,
          140.0,
          141.0,
          142.0,
          143.0,
          144.0,
          145.0,
          146.0,
          147.0,
          148.0,
          149.0,
          150.0,
          151.0,
          152.0,
          153.0,
          154.0,
          155.0,
          156.0,
          157.0,
          158.0,
          159.0,
          160.0,
          161.0,
          162.0,
          163.0,
          164.0,
          165.0,
          166.0,
          167.0,
          168.0,
          169.0,
          170.0,
          171.0,
          172.0,
          173.0,
          174.0,
          175.0,
          176.0,
          177.0,
          178.0,
          179.0,
          180.0,
          181.0,
          182.0,
          183.0,
          184.0,
          185.0,
          186.0,
          187.0,
          188.0,
          189.0,
          190.0,
          191.0,
          192.0,
          193.0,
          194.0,
          195.0,
          196.0,
          197.0,
          198.0,
          199.0,
          200.0,
          201.0,
          202.0,
          203.0,
          204.0,
          205.0,
          206.0,
          207.0,
          208.0,
          209.0,
          210.0,
          211.0,
          212.0,
          213.0,
          214.0,
          215.0,
          216.0,
          217.0,
          218.0,
          219.0,
          220.0,
          221.0,
          222.0,
          223.0,
          224.0,
          225.0,
          226.0,
          227.0,
          228.0,
          229.0,
          230.0,
          231.0,
          232.0,
          233.0,
          234.0,
          235.0,
          236.0,
          237.0,
          238.0,
          239.0,
          240.0,
          241.0,
          242.0,
          243.0,
          244.0,
          245.0,
          246.0,
          247.0,
          248.0,
          249.0,
          250.0,
          251.0,
          252.0,
          253.0,
          254.0,
          255.0,
          256.0,
          257.0,
          258.0,
          259.0,
          260.0,
          261.0,
          262.0,
          263.0,
          264.0,
          265.0,
          266.0,
          267.0,
          268.0,
          269.0,
          270.0,
          271.0,
          272.0,
          273.0,
          274.0
        ],
        "values": [
          0.0,
          0.003058049353185163,
          0.0068286053782041405,
          0.011443333143625181,
          0.017049242227794886,
          0.023808249529996536,
          0.031896083005302105,
          0.04150041235030107,
          0.05281810474796289,
          0.06605152469213953,
          0.08140382734678527,
          0.09907323500947689,
          0.11924633553466712,
          0.14209049875014168,
          0.16774556986080713,
          0.19631506463647916,
          0.22785715612345586,
          0.26237580239034836,
          0.2998124147204064,
          0.3400385009157807,
          0.38284973447839243,
          0.42796189353692415,
          0.47500908071843084,
          0.5235445753551258,
          0.5730445828234091,
          0.6229150346838834,
          0.6725014618298201,
          0.72110181710674,
          0.7679819714674808,
          0.8123934574626038,
          0.8535928951228327,
          0.8908624174030301,
          0.9235303239080921,
          0.9509911397516162,
          0.9727242461939137,
          0.9883102837120941,
          0.9974446060715467,
          0.9999471825599051,
          0.9957684987815987,
          0.9849911858358814,
          0.9678273029960469,
          0.944611398717884,
          0.9157896671592016,
          0.881905691146118,
          0.8435834077626125,
          0.8015080415738548,
          0.7564058175674344,
          0.7090232887079135,
          0.6601070919813476,
          0.6103848851774945,
          0.5605481200722063,
          0.5112371836962315,
          0.46302929684671157,
          0.41642940732693534,
          0.3718641638835477,
          0.3296789139926457,
          0.29013754179382495,
          0.2534248571882333,
          0.21965116711806662,
          0.18885860709358446,
          0.1610287850284882,
          0.13609128863658995,
          0.11393262894866925,
          0.09440523188325659,
          0.07733614263856259,
          0.06253516917442042,
          0.04980225659717192,
          0.038933949669178874,
          0.029728862417013,
          0.02199212917278662,
          0.015538858453245177,
          0.010196648783240283,
          0.005807253574044027,
          0.0022275007775613962,
          0.0,
          0.0,
          0.0,
          0.0,
          0.0,
          0.0,
          0.0,
          0.0,
          0.0,
          0.0,
          0.0,
          0.0,
          0.0,
          0.0,
          0.0,
          0.0,
          0.0,
          0.0,
          0.0,
          0.0,
          0.0,
          0.0,
          0.0,
          0.0,
          0.0,
          0.0,
          0.0,
          0.0,
          0.0,
          0.0,
          0.0,
          0.0,
          0.0,
          0.0,
          0.0,
          0.0,
          0.0,
          0.0,
          0.0,
          0.0,
          0.0,
          0.0,
          0.0,
          0.0,
          0.0,
          0.0,
          0.0,
          0.0,
          0.0,
          0.0,
          0.0,
          0.0,
          0.0,
          0.0,
          0.0,
          0.0,
          0.0,
          0.0,
          0.0,
          0.0,
          0.0,
          0.0,
          0.0,
          0.0,
          0.0,
          0.0,
          0.0,
          0.0,
          0.0,
          0.0,
          0.0,
          0.0,
          0.0,
          0.0,
          0.0,
          0.0,
          0.0,
          0.0,
          0.0,
          0.0,
          0.0,
          0.0,
          0.0,
          0.0,
          0.0,
          0.0,
          0.0,
          0.0,
          0.0,
          0.0,
          0.0,
          0.0,
          0.0,
          0.0,
          0.0,
          0.0,
          0.0,
          0.0,
          0.0,
          0.0,
          0.0,
          0.0,
          0.0,
          0.0,
          0.0,
          0.0,
          0.0,
          0.0,
          0.0,
          0.0,
          0.0,
          0.0,
          0.0,
          0.0,
          0.0,
          0.0,
          0.0,
          0.0,
          0.0,
          0.0,
          0.0,
          0.0,
          0.0,
          0.0,
          0.0,
          0.0,
          0.0,
          0.0,
          0.0,
          0.0,
          0.0,
          0.0,
          0.0,
          0.0,
          0.0,
          0.0,
          0.0,
          0.0,
          0.0,
          0.0,
          0.0,
          0.0,
          0.0,
          0.0,
          0.0,
          0.0,
          0.0,
          0.0,
          0.0,
          0.0,
          0.0,
          0.0,
          0.0,
          0.0,
          0.0,
          0.0,
          0.0,
          0.0,
          0.0,
          0.0,
          0.0,
          0.0,
          0.0,
          0.0,
          0.0,
          0.0,
          0.0,
          0.0,
          0.0,
          0.0,
          0.0,
          0.0,
          0.0,
          0.0,
          0.0,
          0.0,
          0.0,
          0.0,
          0.0,
          0.0,
          0.0,
          0.0,
          0.0,
          0.0,
          0.0,
          0.0,
          0.0,
          0.0,
          0.0,
          0.0,
          0.0,
          0.0,
          0.0,
          0.0,
          0.0,
          0.0,
          0.0,
          0.0,
          0.0,
          0.0,
          0.0
        ],
        "scale": 0.25
      }
    ],
    "collapse_operators": [],
    "h_terms": [
      {
        "type": "drive",
        "source": "pulse_ir",
        "channels": [
          "RO0",
          "XY0"
        ]
      }
    ],
    "noise_terms": [
      {
        "type": "lindblad"
      }
    ],
    "noise_cfg": {
      "gamma1": 0.0,
      "gamma_phi": 0.0
    }
  }
}